monadsquishy/__init__.py
monadsquishy/functions.py
monadsquishy/squishy.py
monadsquishy-0.1.2.dist-info/LICENSE
monadsquishy-0.1.2.dist-info/METADATA
monadsquishy-0.1.2.dist-info/WHEEL
monadsquishy-0.1.2.dist-info/top_level.txt
monadsquishy-0.1.2.dist-info/RECORD
